flare_utilities/__init__.py
flare_utilities/Reporting/__init__.py
flare_utilities/Reporting/FlareHTMLReporter.py
flare_utilities/Reporting/HTMLBuilder.py
flare_utilities/Reporting/index.html
flare_utilities/Reporting/Report.py
flare_utilities/Reporting/style.css
flare_utilities/Reporting/TestcaseBuilder.py
flare_utilities-0.1.1.dist-info/METADATA
flare_utilities-0.1.1.dist-info/WHEEL
flare_utilities-0.1.1.dist-info/RECORD
