Metadata-Version: 2.1
Name: flare-utilities
Version: 0.1.1
Summary: Flare Utilities having support libraries for Flare-BDD framework for reporting purposes.
Author: Aravinth Alliraj
Requires-Python: >=3.7,<4.0
Classifier: Programming Language :: Python :: 3
Classifier: Programming Language :: Python :: 3.7
Classifier: Programming Language :: Python :: 3.8
Classifier: Programming Language :: Python :: 3.9
Classifier: Programming Language :: Python :: 3.10
Classifier: Programming Language :: Python :: 3.11
Classifier: Programming Language :: Python :: 3.12
